README.md
setup.py
nvidia_clara/__init__.py
nvidia_clara/base_client.py
nvidia_clara/clara_client.py
nvidia_clara/clara_types.py
nvidia_clara/constants.py
nvidia_clara/job_types.py
nvidia_clara/jobs_client.py
nvidia_clara/model_types.py
nvidia_clara/models_client.py
nvidia_clara/payload_types.py
nvidia_clara/payloads_client.py
nvidia_clara/pipeline_types.py
nvidia_clara/pipelines_client.py
nvidia_clara/grpc/__init__.py
nvidia_clara/grpc/clara_pb2.py
nvidia_clara/grpc/clara_pb2_grpc.py
nvidia_clara/grpc/common_pb2.py
nvidia_clara/grpc/common_pb2_grpc.py
nvidia_clara/grpc/jobs_pb2.py
nvidia_clara/grpc/jobs_pb2_grpc.py
nvidia_clara/grpc/metrics_pb2.py
nvidia_clara/grpc/metrics_pb2_grpc.py
nvidia_clara/grpc/models_pb2.py
nvidia_clara/grpc/models_pb2_grpc.py
nvidia_clara/grpc/payloads_pb2.py
nvidia_clara/grpc/payloads_pb2_grpc.py
nvidia_clara/grpc/pipelines_pb2.py
nvidia_clara/grpc/pipelines_pb2_grpc.py
nvidia_clara_client.egg-info/PKG-INFO
nvidia_clara_client.egg-info/SOURCES.txt
nvidia_clara_client.egg-info/dependency_links.txt
nvidia_clara_client.egg-info/requires.txt
nvidia_clara_client.egg-info/top_level.txt