Metadata-Version: 2.1
Name: nvidia-clara-client
Version: 0.8.1
Summary: Python package to interact with Clara Platform Server API
Home-page: https://github.com/NVIDIA/clara-platform-python-client
Author: NVIDIA Clara Deploy
License: Apache Software License (http://www.apache.org/licenses/LICENSE-2.0)
Platform: UNKNOWN
Classifier: Programming Language :: Python :: 3
Classifier: Operating System :: OS Independent
Classifier: License :: OSI Approved :: Apache Software License
Requires-Python: >=3.6
